data/readme.txt
open_webui/__init__.py
open_webui/alembic.ini
open_webui/config.py
open_webui/constants.py
open_webui/env.py
open_webui/functions.py
open_webui/main.py
open_webui/tasks.py
open_webui/data/readme.txt
open_webui/internal/db.py
open_webui/internal/wrappers.py
open_webui/internal/migrations/001_initial_schema.py
open_webui/internal/migrations/002_add_local_sharing.py
open_webui/internal/migrations/003_add_auth_api_key.py
open_webui/internal/migrations/004_add_archived.py
open_webui/internal/migrations/005_add_updated_at.py
open_webui/internal/migrations/006_migrate_timestamps_and_charfields.py
open_webui/internal/migrations/007_add_user_last_active_at.py
open_webui/internal/migrations/008_add_memory.py
open_webui/internal/migrations/009_add_models.py
open_webui/internal/migrations/010_migrate_modelfiles_to_models.py
open_webui/internal/migrations/011_add_user_settings.py
open_webui/internal/migrations/012_add_tools.py
open_webui/internal/migrations/013_add_user_info.py
open_webui/internal/migrations/014_add_files.py
open_webui/internal/migrations/015_add_functions.py
open_webui/internal/migrations/016_add_valves_and_is_active.py
open_webui/internal/migrations/017_add_user_oauth_sub.py
open_webui/internal/migrations/018_add_function_is_global.py
open_webui/migrations/README
open_webui/migrations/env.py
open_webui/migrations/script.py.mako
open_webui/migrations/util.py
open_webui/migrations/versions/1af9b942657b_migrate_tags.py
open_webui/migrations/versions/242a2047eae0_update_chat_table.py
open_webui/migrations/versions/3ab32c4b8f59_update_tags.py
open_webui/migrations/versions/4ace53fd72c8_update_folder_table_datetime.py
open_webui/migrations/versions/57c599a3cb57_add_channel_table.py
open_webui/migrations/versions/6a39f3d8e55c_add_knowledge_table.py
open_webui/migrations/versions/7826ab40b532_update_file_table.py
open_webui/migrations/versions/7e5b5dc7342b_init.py
open_webui/migrations/versions/922e7a387820_add_group_table.py
open_webui-0.5.2.dist-info/METADATA
open_webui-0.5.2.dist-info/WHEEL
open_webui-0.5.2.dist-info/entry_points.txt
open_webui-0.5.2.dist-info/licenses/LICENSE
open_webui-0.5.2.dist-info/RECORD
