Metadata-Version: 2.4
Name: open-webui
Version: 0.5.2
Summary: Open WebUI
Author-email: Timothy Jaeryang Baek <tim@openwebui.com>
License: MIT License
License-File: LICENSE
Classifier: Development Status :: 4 - Beta
Classifier: License :: OSI Approved :: MIT License
Classifier: Programming Language :: Python :: 3
Classifier: Programming Language :: Python :: 3.11
Classifier: Programming Language :: Python :: 3.12
Classifier: Topic :: Communications :: Chat
Classifier: Topic :: Multimedia
Requires-Python: <3.13.0a1,>=3.11
Requires-Dist: aiocache
Requires-Dist: aiofiles
Requires-Dist: aiohttp==3.11.8
Requires-Dist: alembic==1.14.0
Requires-Dist: anthropic
Requires-Dist: apscheduler==3.10.4
Requires-Dist: argon2-cffi==23.1.0
Requires-Dist: async-timeout
Requires-Dist: authlib==1.3.2
Requires-Dist: bcrypt==4.2.0
Requires-Dist: black==24.8.0
Requires-Dist: boto3==1.35.53
Requires-Dist: chromadb==0.5.15
Requires-Dist: colbert-ai==0.2.21
Requires-Dist: docker~=7.1.0
Requires-Dist: docx2txt==0.8
Requires-Dist: duckduckgo-search~=6.3.5
Requires-Dist: einops==0.8.0
Requires-Dist: extract-msg
Requires-Dist: fake-useragent==1.5.1
Requires-Dist: fastapi==0.111.0
Requires-Dist: faster-whisper==1.0.3
Requires-Dist: flask-cors==5.0.0
Requires-Dist: flask==3.0.3
Requires-Dist: fpdf2==2.7.9
Requires-Dist: ftfy==6.2.3
Requires-Dist: google-generativeai==0.7.2
Requires-Dist: googleapis-common-protos==1.63.2
Requires-Dist: langchain-chroma==0.1.4
Requires-Dist: langchain-community==0.3.7
Requires-Dist: langchain==0.3.7
Requires-Dist: langfuse==2.44.0
Requires-Dist: ldap3==2.9.1
Requires-Dist: markdown==3.7
Requires-Dist: nltk==3.9.1
Requires-Dist: openai
Requires-Dist: opencv-python-headless==4.10.0.84
Requires-Dist: openpyxl==3.1.5
Requires-Dist: opensearch-py==2.7.1
Requires-Dist: pandas==2.2.3
Requires-Dist: passlib[bcrypt]==1.7.4
Requires-Dist: peewee-migrate==1.12.2
Requires-Dist: peewee==3.17.6
Requires-Dist: pgvector==0.3.5
Requires-Dist: psutil
Requires-Dist: psycopg2-binary==2.9.9
Requires-Dist: pydantic==2.9.2
Requires-Dist: pydub
Requires-Dist: pyjwt[crypto]==2.9.0
Requires-Dist: pymdown-extensions==10.11.2
Requires-Dist: pymilvus==2.5.0
Requires-Dist: pymongo
Requires-Dist: pymysql==1.1.1
Requires-Dist: pypandoc==1.13
Requires-Dist: pypdf==4.3.1
Requires-Dist: pytest-docker~=3.1.1
Requires-Dist: pytest~=8.3.2
Requires-Dist: python-jose==3.3.0
Requires-Dist: python-multipart==0.0.18
Requires-Dist: python-pptx==1.0.0
Requires-Dist: python-socketio==5.11.3
Requires-Dist: pytube==15.0.0
Requires-Dist: pyxlsb==1.0.10
Requires-Dist: qdrant-client~=1.12.0
Requires-Dist: rank-bm25==0.2.2
Requires-Dist: rapidocr-onnxruntime==1.3.24
Requires-Dist: redis
Requires-Dist: requests==2.32.3
Requires-Dist: sentence-transformers==3.3.1
Requires-Dist: sentencepiece
Requires-Dist: soundfile==0.12.1
Requires-Dist: sqlalchemy==2.0.32
Requires-Dist: tiktoken
Requires-Dist: unstructured==0.15.9
Requires-Dist: uvicorn[standard]==0.30.6
Requires-Dist: validators==0.33.0
Requires-Dist: xlrd==2.0.1
Requires-Dist: youtube-transcript-api==0.6.3
